pymcl/__init__.py
pymcl/_pymcl.cp312-win_amd64.pyd
pymcl/_pymcl.cpp
pymcl/_pymcl.pyi
pymcl/py.typed
pymcl-1.0.2.dist-info/licenses/LICENSE
pymcl-1.0.2.dist-info/METADATA
pymcl-1.0.2.dist-info/WHEEL
pymcl-1.0.2.dist-info/top_level.txt
pymcl-1.0.2.dist-info/RECORD
