Metadata-Version: 2.4
Name: pymcl
Version: 1.0.2
Summary: A Python 3 wrapper for the mcl library (BLS12-381) using Pybind11.
Author-email: Jemtaly <Jemtaly@outlook.com>
License: MIT License
Project-URL: Homepage, https://www.github.com/Jemtaly/pymcl
Project-URL: Repository, https://www.github.com/Jemtaly/pymcl
Classifier: Programming Language :: Python :: 3
Classifier: Programming Language :: Python :: 3.10
Classifier: Programming Language :: Python :: 3.11
Classifier: Programming Language :: Python :: 3.12
Classifier: License :: OSI Approved :: MIT License
Classifier: Operating System :: OS Independent
Classifier: Development Status :: 4 - Beta
Requires-Python: >=3.10
License-File: LICENSE
Provides-Extra: test
Requires-Dist: pytest>=7; extra == "test"
Dynamic: license-file
